apitoolkit_fastapi/__init__.py
apitoolkit_fastapi-2.0.0.dist-info/METADATA
apitoolkit_fastapi-2.0.0.dist-info/WHEEL
apitoolkit_fastapi-2.0.0.dist-info/top_level.txt
apitoolkit_fastapi-2.0.0.dist-info/RECORD
