Metadata-Version: 2.1
Name: apitoolkit-fastapi
Version: 2.0.0
Author: APIToolkit
Author-email: hello@apitoolkit.io
Requires-Dist: fastapi
Requires-Dist: apitoolkit-common
Requires-Dist: opentelemetry-api>=1.0.0
